{
	"sourceDataInfo": {
		"newsID": "IS_M10_352567",
		"newsCategory": "IT&과학",
		"newsSubcategory": "IT/과학, 헬스 > 인터넷/보안",
		"newsTitle": "\\\"갤럭시Z플립3 아닙니다\\\"…화웨이 폴더블폰, 같은듯 다른듯",
		"newsSubTitle": "null",
		"newsContent": "중국 IT기업 화웨이가 삼성의 갤럭시Z플립3를 닮은 폴더블폰(접이식 폰) 출시를 예고했다.\n화웨이는 삼성이 시도한 클램셸(조개껍데기처럼 여닫는 형태) 디자인을 적용한 스마트폰으로 폴더블폰 시장에 도전한다. 19일 더버지 등 해외 IT매체에 따르면 화웨이는 최근 자사 웨이보 계정을 통해 오는 23일 오후 3시30분(중국 현지시간) 동계 신제품 출시 행사를 열고 자사 폴더블폰 P50포켓을 공개하겠다고 밝혔다.\n더버지는 \\\"삼성 Z플립 또는 모토로라 레이저(Razr)와 유사한 디자인\\\"이라고 소개했다.\n화웨이는 이와 함께 패션잡지 하퍼스바자 차이나에 P50 화보를 게재했다.\n화웨이가 공개한 화보에 따르면 P50포켓은 갤럭시Z플립3처럼 바(bar) 형태 스마트폰을 상하로 접은 모양이다.\n색상은 금색 또는 은색으로 추정된다.\nP50포켓은 겉면 카메라와 외부 액정이 원형인 것이 특징이다.\n총 3개의 카메라와 LED 1개가 배치됐다.\n시간 등을 확인할 수 있는 원형 외부 액정은 크지 않은 것으로 보인다.\n화웨이는 올 초에도 갤럭시Z폴드3처럼 태블릿PC 하나를 반으로 접는 형태의 '메이트X' 시리즈를 출시했지만 크게 흥행하지 못했다.\n최대 300만원에 이르는 높은 출고가 탓이었다.\n외신에 따르면 P50포켓은 오는 7월께 중국에서만 출시될 전망이다.\n더버지는 \\\"P50포켓이 글로벌 시장에 출시될지 여부나 시기는 불분명하다\\\"고 전했다.",
		"partNum": "P1",
		"useType": 1,
		"processType": "A",
		"processPattern": "00",
		"processLevel": "하",
		"sentenceCount": 13,
		"sentenceInfo": [
			{
				"sentenceNo": 1,
				"sentenceContent": "중국 IT기업 화웨이가 삼성의 갤럭시Z플립3를 닮은 폴더블폰(접이식 폰) 출시를 예고했다.",
				"sentenceSize": 50
			},
			{
				"sentenceNo": 2,
				"sentenceContent": "화웨이는 삼성이 시도한 클램셸(조개껍데기처럼 여닫는 형태) 디자인을 적용한 스마트폰으로 폴더블폰 시장에 도전한다. 19일 더버지 등 해외 IT매체에 따르면 화웨이는 최근 자사 웨이보 계정을 통해 오는 23일 오후 3시30분(중국 현지시간) 동계 신제품 출시 행사를 열고 자사 폴더블폰 P50포켓을 공개하겠다고 밝혔다.",
				"sentenceSize": 177
			},
			{
				"sentenceNo": 3,
				"sentenceContent": "더버지는 \\\"삼성 Z플립 또는 모토로라 레이저(Razr)와 유사한 디자인\\\"이라고 소개했다.",
				"sentenceSize": 51
			},
			{
				"sentenceNo": 4,
				"sentenceContent": "화웨이는 이와 함께 패션잡지 하퍼스바자 차이나에 P50 화보를 게재했다.",
				"sentenceSize": 40
			},
			{
				"sentenceNo": 5,
				"sentenceContent": "화웨이가 공개한 화보에 따르면 P50포켓은 갤럭시Z플립3처럼 바(bar) 형태 스마트폰을 상하로 접은 모양이다.",
				"sentenceSize": 62
			},
			{
				"sentenceNo": 6,
				"sentenceContent": "색상은 금색 또는 은색으로 추정된다.",
				"sentenceSize": 20
			},
			{
				"sentenceNo": 7,
				"sentenceContent": "P50포켓은 겉면 카메라와 외부 액정이 원형인 것이 특징이다.",
				"sentenceSize": 34
			},
			{
				"sentenceNo": 8,
				"sentenceContent": "총 3개의 카메라와 LED 1개가 배치됐다.",
				"sentenceSize": 24
			},
			{
				"sentenceNo": 9,
				"sentenceContent": "시간 등을 확인할 수 있는 원형 외부 액정은 크지 않은 것으로 보인다.",
				"sentenceSize": 39
			},
			{
				"sentenceNo": 10,
				"sentenceContent": "화웨이는 올 초에도 갤럭시Z폴드3처럼 태블릿PC 하나를 반으로 접는 형태의 '메이트X' 시리즈를 출시했지만 크게 흥행하지 못했다.",
				"sentenceSize": 72
			},
			{
				"sentenceNo": 11,
				"sentenceContent": "최대 300만원에 이르는 높은 출고가 탓이었다.",
				"sentenceSize": 26
			},
			{
				"sentenceNo": 12,
				"sentenceContent": "외신에 따르면 P50포켓은 오는 7월께 중국에서만 출시될 전망이다.",
				"sentenceSize": 37
			},
			{
				"sentenceNo": 13,
				"sentenceContent": "더버지는 \\\"P50포켓이 글로벌 시장에 출시될지 여부나 시기는 불분명하다\\\"고 전했다.",
				"sentenceSize": 48
			}
		]
	},
	"labeledDataInfo": {
		"newTitle": "\\\"갤럭시Z플립3 아닙니다\\\"…화웨이 폴더블폰, 같은듯 다른듯",
		"clickbaitClass": 1,
		"referSentenceInfo": [
			{
				"sentenceNo": 1,
				"referSentenceyn": "N"
			},
			{
				"sentenceNo": 2,
				"referSentenceyn": "N"
			},
			{
				"sentenceNo": 3,
				"referSentenceyn": "N"
			},
			{
				"sentenceNo": 4,
				"referSentenceyn": "N"
			},
			{
				"sentenceNo": 5,
				"referSentenceyn": "N"
			},
			{
				"sentenceNo": 6,
				"referSentenceyn": "N"
			},
			{
				"sentenceNo": 7,
				"referSentenceyn": "N"
			},
			{
				"sentenceNo": 8,
				"referSentenceyn": "N"
			},
			{
				"sentenceNo": 9,
				"referSentenceyn": "N"
			},
			{
				"sentenceNo": 10,
				"referSentenceyn": "N"
			},
			{
				"sentenceNo": 11,
				"referSentenceyn": "N"
			},
			{
				"sentenceNo": 12,
				"referSentenceyn": "N"
			},
			{
				"sentenceNo": 13,
				"referSentenceyn": "N"
			}
		]
	}
}