{
	"sourceDataInfo": {
		"newsID": "IS_M14_324324",
		"newsCategory": "IT&과학",
		"newsSubcategory": "콘텐츠",
		"newsTitle": "n번방 방지법, 과방위 법안소위 통과",
		"newsSubTitle": "",
		"newsContent": "디지털 성범죄를 방지하기 위한 일명 'n번방 방지법'이 국회 과학기술정보방송통신위원회 정보통신방송법안심사소위(이하 소위)를 통과했다.\n인터넷 업계는 통신망 유통 정보 확인 권한이 없어 필터링 등 기술 조치 의무화는 부당하다고 주장했지만 받아들여지지 않았다.\n국회 과학기술정보방송통신위원회 정보통신방송법안심사소위(이하 소위)는 6일 오후 20대 국회 마지막 소위원회를 열고 소프트웨어산업 진흥법 개정안, 국가정보화 기본법, 전기통신사업법 개정안 등을 논의했다.\n인터넷 업계 시선은 디지털 성범죄 방지를 위한 정보통신망법 개정안에 쏠렸다.\n일명 'n번방 방지법'으로 불리는 개정안은 1만5000여 전체 부가통신사업자에 디지털 성범죄물 유통 방지를 위한 조치(필터링 등)를 취하도록 의무화했다.\n포털, 메신저, 소셜네트워크서비스(SNS) 등 인터넷 업계는 통신비밀보호법 때문에 기술적 조치가 어려울 뿐더러 해외 사업자에는 실효성이 없는 법안이라며 반발했다.\n서비스 다양성을 제한하고 자칫 사생활 침해 우려도 있다는 지적이다.\n소위 논의 방향은 크게 4가지로 예상됐다.\n당정 의지가 강하고 여야 위원이 합의한 만큼 법안이 소위를 통과, 상임위원회로 제출되는 게 첫 번째, 논의 과정에서 인터넷 업계와 전문가 의견을 반영, 일부 내용을 완화해 통과시키는 게 두 번째 시나리오다. '결의안'만 채택될 가능성도 있었다.\n이원욱 더불어민주당 의원은 '디지털 성범죄물과 범죄자 처벌을 위한 국제공조 구축'과 '역외규정 도입' '부가통신사업자 즉시 삭제 및 필터링 등 사전적 기술 도입' 등 결의안을 제출했다.\n6일 소위 처리 안건이 29개에 달하고 시간은 부족하기 때문에 논의 자체를 하지 못하는 게 마지막 시나리오였다.\n이 경우 이번 국회에서 n번방 관련 논의는 더이상 처리가 어려워진다.\n그러나 소위는 이원욱 더불어민주당 의원이 발의한 전기통신사업법 개정안과 정보통신망법 개정안을 통과시켜 상임위로 넘겼다.\n전기통신사업법 개정안은 인터넷 사업자 통신망에 필터링을 설치하는 게 핵심이다.\n정보통신망법 개정안은 역외규정, 책임자지정, 투명성보고 등이 담겼다.\n과방위는 7일 상임위 전체회의를 열고 해당 법안을 논의한다.\n상임위를 통과하면 법제사법위원회, 국회 본회의를 거친다.\n앞서 국회는 지난달 29일 본회의에서 성폭력범죄의 처벌 등에 관한 특례법 개정안, 형법 개정안, 범죄수익은닉의 규제 및 처벌 등에 관한 법률 개정안 등 범죄자를 대상으로 한 'n번방 재발방지 3법'을 통과시켰다.",
		"partNum": "P1",
		"useType": 1,
		"processType": "A",
		"processPattern": "00",
		"processLevel": "하",
		"sentenceCount": 18,
		"sentenceInfo": [
			{
				"sentenceNo": 1,
				"sentenceContent": "디지털 성범죄를 방지하기 위한 일명 'n번방 방지법'이 국회 과학기술정보방송통신위원회 정보통신방송법안심사소위(이하 소위)를 통과했다.",
				"sentenceSize": 74
			},
			{
				"sentenceNo": 2,
				"sentenceContent": "인터넷 업계는 통신망 유통 정보 확인 권한이 없어 필터링 등 기술 조치 의무화는 부당하다고 주장했지만 받아들여지지 않았다.",
				"sentenceSize": 68
			},
			{
				"sentenceNo": 3,
				"sentenceContent": "국회 과학기술정보방송통신위원회 정보통신방송법안심사소위(이하 소위)는 6일 오후 20대 국회 마지막 소위원회를 열고 소프트웨어산업 진흥법 개정안, 국가정보화 기본법, 전기통신사업법 개정안 등을 논의했다.",
				"sentenceSize": 112
			},
			{
				"sentenceNo": 4,
				"sentenceContent": "인터넷 업계 시선은 디지털 성범죄 방지를 위한 정보통신망법 개정안에 쏠렸다.",
				"sentenceSize": 42
			},
			{
				"sentenceNo": 5,
				"sentenceContent": "일명 'n번방 방지법'으로 불리는 개정안은 1만5000여 전체 부가통신사업자에 디지털 성범죄물 유통 방지를 위한 조치(필터링 등)를 취하도록 의무화했다.",
				"sentenceSize": 85
			},
			{
				"sentenceNo": 6,
				"sentenceContent": "포털, 메신저, 소셜네트워크서비스(SNS) 등 인터넷 업계는 통신비밀보호법 때문에 기술적 조치가 어려울 뿐더러 해외 사업자에는 실효성이 없는 법안이라며 반발했다.",
				"sentenceSize": 90
			},
			{
				"sentenceNo": 7,
				"sentenceContent": "서비스 다양성을 제한하고 자칫 사생활 침해 우려도 있다는 지적이다.",
				"sentenceSize": 37
			},
			{
				"sentenceNo": 8,
				"sentenceContent": "소위 논의 방향은 크게 4가지로 예상됐다.",
				"sentenceSize": 23
			},
			{
				"sentenceNo": 9,
				"sentenceContent": "당정 의지가 강하고 여야 위원이 합의한 만큼 법안이 소위를 통과, 상임위원회로 제출되는 게 첫 번째, 논의 과정에서 인터넷 업계와 전문가 의견을 반영, 일부 내용을 완화해 통과시키는 게 두 번째 시나리오다. '결의안'만 채택될 가능성도 있었다.",
				"sentenceSize": 136
			},
			{
				"sentenceNo": 10,
				"sentenceContent": "이원욱 더불어민주당 의원은 '디지털 성범죄물과 범죄자 처벌을 위한 국제공조 구축'과 '역외규정 도입' '부가통신사업자 즉시 삭제 및 필터링 등 사전적 기술 도입' 등 결의안을 제출했다.",
				"sentenceSize": 103
			},
			{
				"sentenceNo": 11,
				"sentenceContent": "6일 소위 처리 안건이 29개에 달하고 시간은 부족하기 때문에 논의 자체를 하지 못하는 게 마지막 시나리오였다.",
				"sentenceSize": 62
			},
			{
				"sentenceNo": 12,
				"sentenceContent": "이 경우 이번 국회에서 n번방 관련 논의는 더이상 처리가 어려워진다.",
				"sentenceSize": 38
			},
			{
				"sentenceNo": 13,
				"sentenceContent": "그러나 소위는 이원욱 더불어민주당 의원이 발의한 전기통신사업법 개정안과 정보통신망법 개정안을 통과시켜 상임위로 넘겼다.",
				"sentenceSize": 66
			},
			{
				"sentenceNo": 14,
				"sentenceContent": "전기통신사업법 개정안은 인터넷 사업자 통신망에 필터링을 설치하는 게 핵심이다.",
				"sentenceSize": 43
			},
			{
				"sentenceNo": 15,
				"sentenceContent": "정보통신망법 개정안은 역외규정, 책임자지정, 투명성보고 등이 담겼다.",
				"sentenceSize": 38
			},
			{
				"sentenceNo": 16,
				"sentenceContent": "과방위는 7일 상임위 전체회의를 열고 해당 법안을 논의한다.",
				"sentenceSize": 33
			},
			{
				"sentenceNo": 17,
				"sentenceContent": "상임위를 통과하면 법제사법위원회, 국회 본회의를 거친다.",
				"sentenceSize": 31
			},
			{
				"sentenceNo": 18,
				"sentenceContent": "앞서 국회는 지난달 29일 본회의에서 성폭력범죄의 처벌 등에 관한 특례법 개정안, 형법 개정안, 범죄수익은닉의 규제 및 처벌 등에 관한 법률 개정안 등 범죄자를 대상으로 한 'n번방 재발방지 3법'을 통과시켰다.",
				"sentenceSize": 118
			}
		]
	},
	"labeledDataInfo": {
		"newTitle": "n번방 방지법, 과방위 법안소위 통과",
		"clickbaitClass": 1,
		"referSentenceInfo": [
			{
				"sentenceNo": 1,
				"referSentenceyn": "N"
			},
			{
				"sentenceNo": 2,
				"referSentenceyn": "N"
			},
			{
				"sentenceNo": 3,
				"referSentenceyn": "N"
			},
			{
				"sentenceNo": 4,
				"referSentenceyn": "N"
			},
			{
				"sentenceNo": 5,
				"referSentenceyn": "N"
			},
			{
				"sentenceNo": 6,
				"referSentenceyn": "N"
			},
			{
				"sentenceNo": 7,
				"referSentenceyn": "N"
			},
			{
				"sentenceNo": 8,
				"referSentenceyn": "N"
			},
			{
				"sentenceNo": 9,
				"referSentenceyn": "N"
			},
			{
				"sentenceNo": 10,
				"referSentenceyn": "N"
			},
			{
				"sentenceNo": 11,
				"referSentenceyn": "N"
			},
			{
				"sentenceNo": 12,
				"referSentenceyn": "N"
			},
			{
				"sentenceNo": 13,
				"referSentenceyn": "N"
			},
			{
				"sentenceNo": 14,
				"referSentenceyn": "N"
			},
			{
				"sentenceNo": 15,
				"referSentenceyn": "N"
			},
			{
				"sentenceNo": 16,
				"referSentenceyn": "N"
			},
			{
				"sentenceNo": 17,
				"referSentenceyn": "N"
			},
			{
				"sentenceNo": 18,
				"referSentenceyn": "N"
			}
		]
	}
}