{
	"sourceDataInfo": {
		"newsID": "IS_M14_329464",
		"newsCategory": "IT&과학",
		"newsSubcategory": "의료바이오",
		"newsTitle": "리베이트 혐의로 위기 몰린 '동아제약'…제약업계 불안 확산",
		"newsSubTitle": "",
		"newsContent": "검찰 리베이트 수사로 동아제약이 경영위기에 몰렸다.\n제약업계는 리베이트 수사가 업계 전반으로 확산될까 우려한다. 9일 제약업계에 따르면 검찰은 최근 강정석 동아쏘시오홀딩스 회장을 소환해 조사했다.\n병원 관계자에게 금품을 제공한 혐의(약사법 위반)로 동아에스티 전직 영업본부장 2명도 구속했다.\n동아제약은 2013년 지주회사인 동아쏘시오홀딩스로 전환했고 자회사로 전문의약품은 동아에스티가, 일반의약품은 동아제약이 각각 맡고 있다.\n올해 1월 경영권을 물려받은 강 회장은 회사자금 일부를 의료계 리베이트나 접대비 등에 사용하는 데 관여한 혐의(약사법 위반 등)를 받고 있다.\n검찰은 올해 1월과 2월 의약품 리베이트 비리 의혹을 수사하면서 제약사와 병원, 건강보험심사평가원 등으로 수사를 확대했다.\n지난 3월 동아제약 등 3곳에 대해 압수 수색을 벌였다.\n이 수사로 리베이트를 제공한 혐의를 받은 동아에스티 전직 영업본부장이 구속됐다.\n이들은 2012년부터 동아제약 전국 지점을 통해 병원 관계자에게 걸쳐 33억원의 리베이트를 제공한 혐의를 받고 있다.\n동아제약은 3개 회사로 분리되기 이전인 2013년 당시에도 병원을 상대로 리베이트를 제공한 혐의로 기소된 바 있다.\n제약업계는 이번 검찰수사가 다른 제약업체로 확대될 가능성에 불안감을 감추지 못한다.\n검찰은 고질병인 리베이트 근절을 위해 수사 의지를 높이고 있다.\n동아제약의 리베이트 수사를 관할 검찰은 올초 LG화학 생명과학본부와 휴온스를 압수수색하기도 했다.\n이와 함께 공정거래위원회가 제약∙바이오 업계에서 특허권을 토대로 이뤄지는 뒷거래 관행에 대해 실태 점검에 착수하기도 했다.\n제약업계 관계자는 \\\"검찰 리베이트 수사 의지가 강해 불안감을 감출 수 없다\\\"며 \\\"또 다른 제약사가 수사 물망에 올랐을 가능성도 커 영업 활동 시 각별히 유의한다\\\"고 말했다.",
		"partNum": "P1",
		"useType": 1,
		"processType": "A",
		"processPattern": "00",
		"processLevel": "하",
		"sentenceCount": 15,
		"sentenceInfo": [
			{
				"sentenceNo": 1,
				"sentenceContent": "검찰 리베이트 수사로 동아제약이 경영위기에 몰렸다.",
				"sentenceSize": 28
			},
			{
				"sentenceNo": 2,
				"sentenceContent": "제약업계는 리베이트 수사가 업계 전반으로 확산될까 우려한다. 9일 제약업계에 따르면 검찰은 최근 강정석 동아쏘시오홀딩스 회장을 소환해 조사했다.",
				"sentenceSize": 80
			},
			{
				"sentenceNo": 3,
				"sentenceContent": "병원 관계자에게 금품을 제공한 혐의(약사법 위반)로 동아에스티 전직 영업본부장 2명도 구속했다.",
				"sentenceSize": 53
			},
			{
				"sentenceNo": 4,
				"sentenceContent": "동아제약은 2013년 지주회사인 동아쏘시오홀딩스로 전환했고 자회사로 전문의약품은 동아에스티가, 일반의약품은 동아제약이 각각 맡고 있다.",
				"sentenceSize": 75
			},
			{
				"sentenceNo": 5,
				"sentenceContent": "올해 1월 경영권을 물려받은 강 회장은 회사자금 일부를 의료계 리베이트나 접대비 등에 사용하는 데 관여한 혐의(약사법 위반 등)를 받고 있다.",
				"sentenceSize": 79
			},
			{
				"sentenceNo": 6,
				"sentenceContent": "검찰은 올해 1월과 2월 의약품 리베이트 비리 의혹을 수사하면서 제약사와 병원, 건강보험심사평가원 등으로 수사를 확대했다.",
				"sentenceSize": 68
			},
			{
				"sentenceNo": 7,
				"sentenceContent": "지난 3월 동아제약 등 3곳에 대해 압수 수색을 벌였다.",
				"sentenceSize": 31
			},
			{
				"sentenceNo": 8,
				"sentenceContent": "이 수사로 리베이트를 제공한 혐의를 받은 동아에스티 전직 영업본부장이 구속됐다.",
				"sentenceSize": 44
			},
			{
				"sentenceNo": 9,
				"sentenceContent": "이들은 2012년부터 동아제약 전국 지점을 통해 병원 관계자에게 걸쳐 33억원의 리베이트를 제공한 혐의를 받고 있다.",
				"sentenceSize": 65
			},
			{
				"sentenceNo": 10,
				"sentenceContent": "동아제약은 3개 회사로 분리되기 이전인 2013년 당시에도 병원을 상대로 리베이트를 제공한 혐의로 기소된 바 있다.",
				"sentenceSize": 64
			},
			{
				"sentenceNo": 11,
				"sentenceContent": "제약업계는 이번 검찰수사가 다른 제약업체로 확대될 가능성에 불안감을 감추지 못한다.",
				"sentenceSize": 46
			},
			{
				"sentenceNo": 12,
				"sentenceContent": "검찰은 고질병인 리베이트 근절을 위해 수사 의지를 높이고 있다.",
				"sentenceSize": 35
			},
			{
				"sentenceNo": 13,
				"sentenceContent": "동아제약의 리베이트 수사를 관할 검찰은 올초 LG화학 생명과학본부와 휴온스를 압수수색하기도 했다.",
				"sentenceSize": 54
			},
			{
				"sentenceNo": 14,
				"sentenceContent": "이와 함께 공정거래위원회가 제약∙바이오 업계에서 특허권을 토대로 이뤄지는 뒷거래 관행에 대해 실태 점검에 착수하기도 했다.",
				"sentenceSize": 68
			},
			{
				"sentenceNo": 15,
				"sentenceContent": "제약업계 관계자는 \\\"검찰 리베이트 수사 의지가 강해 불안감을 감출 수 없다\\\"며 \\\"또 다른 제약사가 수사 물망에 올랐을 가능성도 커 영업 활동 시 각별히 유의한다\\\"고 말했다.",
				"sentenceSize": 100
			}
		]
	},
	"labeledDataInfo": {
		"newTitle": "리베이트 혐의로 위기 몰린 '동아제약'…제약업계 불안 확산",
		"clickbaitClass": 1,
		"referSentenceInfo": [
			{
				"sentenceNo": 1,
				"referSentenceyn": "N"
			},
			{
				"sentenceNo": 2,
				"referSentenceyn": "N"
			},
			{
				"sentenceNo": 3,
				"referSentenceyn": "N"
			},
			{
				"sentenceNo": 4,
				"referSentenceyn": "N"
			},
			{
				"sentenceNo": 5,
				"referSentenceyn": "N"
			},
			{
				"sentenceNo": 6,
				"referSentenceyn": "N"
			},
			{
				"sentenceNo": 7,
				"referSentenceyn": "N"
			},
			{
				"sentenceNo": 8,
				"referSentenceyn": "N"
			},
			{
				"sentenceNo": 9,
				"referSentenceyn": "N"
			},
			{
				"sentenceNo": 10,
				"referSentenceyn": "N"
			},
			{
				"sentenceNo": 11,
				"referSentenceyn": "N"
			},
			{
				"sentenceNo": 12,
				"referSentenceyn": "N"
			},
			{
				"sentenceNo": 13,
				"referSentenceyn": "N"
			},
			{
				"sentenceNo": 14,
				"referSentenceyn": "N"
			},
			{
				"sentenceNo": 15,
				"referSentenceyn": "N"
			}
		]
	}
}