{
	"sourceDataInfo": {
		"newsID": "EC_M02_005079",
		"newsCategory": "경제",
		"newsSubcategory": "IT·통신",
		"newsTitle": "임기 마친 한성숙, 네이버 유럽사업개발 대표로 복귀",
		"newsSubTitle": "커머스·콘텐츠 앞세워 유럽시장 공략 본격화",
		"newsContent": "최근 임기를 마친 한성숙 네이버 전 대표가 유럽으로 향한다. 17일 IT업계에 따르면, 네이버는 최근 한 전 대표를 유럽사업개발 대표로 발령했다.\n현재 네이버는 프랑스에 별도 유럽 법인을 두고 웹툰과 웹소설 등 콘텐츠를 앞세워 공격적인 시장 진출을 예고한 상황이다.\n로봇이나 메타버스 등을 연구하는 조직인 '네이버랩스'의 유럽법인 역시 프랑스에 있다.\n지난해 2월엔 스페인 1위 중고거래 플랫폼 '왈라팝'에 1550억원을 투자하며 커머스 시장에 진출 가능성도 열었다.\n당시 한 전 대표는 \\\"글로벌에서 개성과 친환경, 가성비를 함께 중시하는 Z세대를 중심으로 재판매 시장의 꾸준한 성장이 관측되고 있다\\\"며 \\\"이번 투자는 네이버가 미래 트렌드를 이끌 세대들을 선점해 장기적인 글로벌 성장을 도모할 수 있는 마일스톤(이정표)이 될 수 있도록 왈라팝과 장기적인 글로벌 가능성도 검토해나갈 계획\\\"이라고 밝힌 바 있다.\n다만, 아직 별도의 유럽 사업개발 조직이 꾸려지지는 않은 것으로 알려졌다.\nIT업계에서는 지난 5년 간 검색(서치플랫폼) 위주의 수익구조를 가지고 있던 네이버에서 콘텐츠·커머스라는 신사업을 발굴한 한 전 대표가 회사의 유럽 진출의 초석을 다지는 역할을 할 것이라 기대하고 있다.\n특히 소상공인과 중소업체를 중심으로 하는 네이버 스마트스토어의 노하우를 유럽 시장에 접목할 것이라는 관측이 나오고 있다.\n아울러, 소상공인·창작자 육성 프로그램인 '프로젝트 꽃'이나, 온라인 창업을 돕는 빅데이터 분석도구도 제공될 전망이다.\n네이버 관계자는 데일리임팩트에 \\\"한 전 대표는 국내 시장에서 창작자와 중소상공인 성장 노하우를 바탕으로 글로벌 시장 진출 기회를 창출할 것\\\"이라며 \\\"아직 유럽 사업개발조직의 규모나 구성에 관련해서는 공개가 어렵다\\\"라고 밝혔다.",
		"partNum": "P1",
		"useType": 0,
		"processType": "A",
		"processPattern": "99",
		"processLevel": "하",
		"sentenceCount": 10,
		"sentenceInfo": [
			{
				"sentenceNo": 1,
				"sentenceContent": "최근 임기를 마친 한성숙 네이버 전 대표가 유럽으로 향한다. 17일 IT업계에 따르면, 네이버는 최근 한 전 대표를 유럽사업개발 대표로 발령했다.",
				"sentenceSize": 81
			},
			{
				"sentenceNo": 2,
				"sentenceContent": "현재 네이버는 프랑스에 별도 유럽 법인을 두고 웹툰과 웹소설 등 콘텐츠를 앞세워 공격적인 시장 진출을 예고한 상황이다.",
				"sentenceSize": 66
			},
			{
				"sentenceNo": 3,
				"sentenceContent": "로봇이나 메타버스 등을 연구하는 조직인 '네이버랩스'의 유럽법인 역시 프랑스에 있다.",
				"sentenceSize": 47
			},
			{
				"sentenceNo": 4,
				"sentenceContent": "지난해 2월엔 스페인 1위 중고거래 플랫폼 '왈라팝'에 1550억원을 투자하며 커머스 시장에 진출 가능성도 열었다.",
				"sentenceSize": 64
			},
			{
				"sentenceNo": 5,
				"sentenceContent": "당시 한 전 대표는 \\\"글로벌에서 개성과 친환경, 가성비를 함께 중시하는 Z세대를 중심으로 재판매 시장의 꾸준한 성장이 관측되고 있다\\\"며 \\\"이번 투자는 네이버가 미래 트렌드를 이끌 세대들을 선점해 장기적인 글로벌 성장을 도모할 수 있는 마일스톤(이정표)이 될 수 있도록 왈라팝과 장기적인 글로벌 가능성도 검토해나갈 계획\\\"이라고 밝힌 바 있다.",
				"sentenceSize": 194
			},
			{
				"sentenceNo": 6,
				"sentenceContent": "다만, 아직 별도의 유럽 사업개발 조직이 꾸려지지는 않은 것으로 알려졌다.",
				"sentenceSize": 41
			},
			{
				"sentenceNo": 7,
				"sentenceContent": "IT업계에서는 지난 5년 간 검색(서치플랫폼) 위주의 수익구조를 가지고 있던 네이버에서 콘텐츠·커머스라는 신사업을 발굴한 한 전 대표가 회사의 유럽 진출의 초석을 다지는 역할을 할 것이라 기대하고 있다.",
				"sentenceSize": 113
			},
			{
				"sentenceNo": 8,
				"sentenceContent": "특히 소상공인과 중소업체를 중심으로 하는 네이버 스마트스토어의 노하우를 유럽 시장에 접목할 것이라는 관측이 나오고 있다.",
				"sentenceSize": 67
			},
			{
				"sentenceNo": 9,
				"sentenceContent": "아울러, 소상공인·창작자 육성 프로그램인 '프로젝트 꽃'이나, 온라인 창업을 돕는 빅데이터 분석도구도 제공될 전망이다.",
				"sentenceSize": 66
			},
			{
				"sentenceNo": 10,
				"sentenceContent": "네이버 관계자는 데일리임팩트에 \\\"한 전 대표는 국내 시장에서 창작자와 중소상공인 성장 노하우를 바탕으로 글로벌 시장 진출 기회를 창출할 것\\\"이라며 \\\"아직 유럽 사업개발조직의 규모나 구성에 관련해서는 공개가 어렵다\\\"라고 밝혔다.",
				"sentenceSize": 130
			}
		]
	},
	"labeledDataInfo": {
		"newTitle": "'볼매' 금융사 신탁에 시중자금이 꽂혔다",
		"clickbaitClass": 0,
		"referSentenceInfo": [
			{
				"sentenceNo": 1,
				"referSentenceyn": "N"
			},
			{
				"sentenceNo": 2,
				"referSentenceyn": "N"
			},
			{
				"sentenceNo": 3,
				"referSentenceyn": "N"
			},
			{
				"sentenceNo": 4,
				"referSentenceyn": "N"
			},
			{
				"sentenceNo": 5,
				"referSentenceyn": "N"
			},
			{
				"sentenceNo": 6,
				"referSentenceyn": "N"
			},
			{
				"sentenceNo": 7,
				"referSentenceyn": "N"
			},
			{
				"sentenceNo": 8,
				"referSentenceyn": "N"
			},
			{
				"sentenceNo": 9,
				"referSentenceyn": "N"
			},
			{
				"sentenceNo": 10,
				"referSentenceyn": "N"
			}
		]
	}
}