{
	"sourceDataInfo": {
		"newsID": "EC_M04_015544",
		"newsCategory": "경제",
		"newsSubcategory": "유통/쇼핑",
		"newsTitle": "설 다가올수록 바짝 인상… 야속한 성수품 가격",
		"newsSubTitle": "대부분 품목 지난달보다 올라 주부들 깊은 한숨 이상기온 탓 수급불균형으로 무 44.1% 등 채소가격 폭등",
		"newsContent": "설이 다가올수록 성수품 가격이 인상돼 주부들의 한숨이 깊어지고 있다.\n지속되는 한파로 인해 무, 대파, 배추 등 채소값이 올랐기 때문이다.\n소비자교육중앙회 대전시지부가 1일 지역 백화점 2곳과 대형마트 12곳, SSM(기업형슈퍼마켓) 9곳, 전통시장 7곳 등 총 30곳을 대상으로 '설 성수품 가격 비교 2차 조사'를 벌인 결과 1차 조사(1월 18일)때보다 대부분 품목에서 상승세를 나타냈다.\n유통업체별로 살펴보면 전통시장은 지난달 18일 21만 5465원에서 이달 1일 23만 4781원으로 9.0% 인상돼 업체 중 가장 큰 상승폭을 보였다.\n이어 백화점은 같은 기간 36만 4705원에서 37만 3859원으로, SSM은 26만 167원에서 26만 4825원으로 각각 2.5%, 1.8% 올랐다.\n대형유통매장은 27만 1400원에서 27만 1722원으로 0.3% 상승해 큰 변동이 없었다.\n설 성수품 평균가격을 살펴보면 대파(500g)는 1차 1700원에서 2차 2450원으로, 무(1.5㎏)는 1262원에서 1818원으로 각각 44.1% 치솟았다.\n배추(2㎏)도 같은 기간 2020원에서 2695원으로 33.4%, 양파(1.5㎏)는 3917원에서 4436원으로 13.2% 인상됐다.\n도라지(국산·400g)는 1만 529원에서 1만 1797원으로 12.0%, 계란(일반란·1판)은 4553원에서 5024원으로 10.3% 값이 올랐다.\n쇠고기(등심·100g)도 9418원에서 1만 4원으로 6.2% 상승했다.\n반면 가래떡(2㎏)은 1만 947원에서 1만 212원으로 6.7%, 식용류는 5697원에서 5446원으로 4.4% 인하됐다.\n이는 채소류가 지난해 고온이상과 올해 들어 이어진 한파로 인한 수급불균형이 주된 원인이라고 소비자교육중앙회 대전시지부는 진단했다.\n소비자교육중앙회 대전시지부는 설 차례상을 전통시장에서 구입할 경우 백화점에서 구매하는 것보다 13만 9078원이 저렴해 소비자의 현명한 선택이 요구된다고 조언했다.\n소비자교육중앙회 대전시지부 관계자는 “명절이 되면 물가당국과 각 지자체에서 물가대책 종합상황실을 운영, 물가안정 대책을 발표하고 있지만 조사에서도 보여지 듯 설 물가에 큰 효과가 없다”며 “같은 유통업체라고 하더라도 품목마다 구입시기별로 가격대가 달라져 할인 행사를 하는지 꼼꼼하게 확인하는 지혜가 필요하다”고 제안했다.",
		"partNum": "P1",
		"useType": 0,
		"processType": "A",
		"processPattern": "99",
		"processLevel": "하",
		"sentenceCount": 14,
		"sentenceInfo": [
			{
				"sentenceNo": 1,
				"sentenceContent": "설이 다가올수록 성수품 가격이 인상돼 주부들의 한숨이 깊어지고 있다.",
				"sentenceSize": 38
			},
			{
				"sentenceNo": 2,
				"sentenceContent": "지속되는 한파로 인해 무, 대파, 배추 등 채소값이 올랐기 때문이다.",
				"sentenceSize": 38
			},
			{
				"sentenceNo": 3,
				"sentenceContent": "소비자교육중앙회 대전시지부가 1일 지역 백화점 2곳과 대형마트 12곳, SSM(기업형슈퍼마켓) 9곳, 전통시장 7곳 등 총 30곳을 대상으로 '설 성수품 가격 비교 2차 조사'를 벌인 결과 1차 조사(1월 18일)때보다 대부분 품목에서 상승세를 나타냈다.",
				"sentenceSize": 142
			},
			{
				"sentenceNo": 4,
				"sentenceContent": "유통업체별로 살펴보면 전통시장은 지난달 18일 21만 5465원에서 이달 1일 23만 4781원으로 9.0% 인상돼 업체 중 가장 큰 상승폭을 보였다.",
				"sentenceSize": 84
			},
			{
				"sentenceNo": 5,
				"sentenceContent": "이어 백화점은 같은 기간 36만 4705원에서 37만 3859원으로, SSM은 26만 167원에서 26만 4825원으로 각각 2.5%, 1.8% 올랐다.",
				"sentenceSize": 85
			},
			{
				"sentenceNo": 6,
				"sentenceContent": "대형유통매장은 27만 1400원에서 27만 1722원으로 0.3% 상승해 큰 변동이 없었다.",
				"sentenceSize": 51
			},
			{
				"sentenceNo": 7,
				"sentenceContent": "설 성수품 평균가격을 살펴보면 대파(500g)는 1차 1700원에서 2차 2450원으로, 무(1.5㎏)는 1262원에서 1818원으로 각각 44.1% 치솟았다.",
				"sentenceSize": 89
			},
			{
				"sentenceNo": 8,
				"sentenceContent": "배추(2㎏)도 같은 기간 2020원에서 2695원으로 33.4%, 양파(1.5㎏)는 3917원에서 4436원으로 13.2% 인상됐다.",
				"sentenceSize": 74
			},
			{
				"sentenceNo": 9,
				"sentenceContent": "도라지(국산·400g)는 1만 529원에서 1만 1797원으로 12.0%, 계란(일반란·1판)은 4553원에서 5024원으로 10.3% 값이 올랐다.",
				"sentenceSize": 83
			},
			{
				"sentenceNo": 10,
				"sentenceContent": "쇠고기(등심·100g)도 9418원에서 1만 4원으로 6.2% 상승했다.",
				"sentenceSize": 40
			},
			{
				"sentenceNo": 11,
				"sentenceContent": "반면 가래떡(2㎏)은 1만 947원에서 1만 212원으로 6.7%, 식용류는 5697원에서 5446원으로 4.4% 인하됐다.",
				"sentenceSize": 69
			},
			{
				"sentenceNo": 12,
				"sentenceContent": "이는 채소류가 지난해 고온이상과 올해 들어 이어진 한파로 인한 수급불균형이 주된 원인이라고 소비자교육중앙회 대전시지부는 진단했다.",
				"sentenceSize": 72
			},
			{
				"sentenceNo": 13,
				"sentenceContent": "소비자교육중앙회 대전시지부는 설 차례상을 전통시장에서 구입할 경우 백화점에서 구매하는 것보다 13만 9078원이 저렴해 소비자의 현명한 선택이 요구된다고 조언했다.",
				"sentenceSize": 91
			},
			{
				"sentenceNo": 14,
				"sentenceContent": "소비자교육중앙회 대전시지부 관계자는 “명절이 되면 물가당국과 각 지자체에서 물가대책 종합상황실을 운영, 물가안정 대책을 발표하고 있지만 조사에서도 보여지 듯 설 물가에 큰 효과가 없다”며 “같은 유통업체라고 하더라도 품목마다 구입시기별로 가격대가 달라져 할인 행사를 하는지 꼼꼼하게 확인하는 지혜가 필요하다”고 제안했다.",
				"sentenceSize": 179
			}
		]
	},
	"labeledDataInfo": {
		"newTitle": "KB국민은행, 혁신기업 4600억 보증 공급..코로나19 피해 기업 우선 지원",
		"clickbaitClass": 0,
		"referSentenceInfo": [
			{
				"sentenceNo": 1,
				"referSentenceyn": "N"
			},
			{
				"sentenceNo": 2,
				"referSentenceyn": "N"
			},
			{
				"sentenceNo": 3,
				"referSentenceyn": "N"
			},
			{
				"sentenceNo": 4,
				"referSentenceyn": "N"
			},
			{
				"sentenceNo": 5,
				"referSentenceyn": "N"
			},
			{
				"sentenceNo": 6,
				"referSentenceyn": "N"
			},
			{
				"sentenceNo": 7,
				"referSentenceyn": "N"
			},
			{
				"sentenceNo": 8,
				"referSentenceyn": "N"
			},
			{
				"sentenceNo": 9,
				"referSentenceyn": "N"
			},
			{
				"sentenceNo": 10,
				"referSentenceyn": "N"
			},
			{
				"sentenceNo": 11,
				"referSentenceyn": "N"
			},
			{
				"sentenceNo": 12,
				"referSentenceyn": "N"
			},
			{
				"sentenceNo": 13,
				"referSentenceyn": "N"
			},
			{
				"sentenceNo": 14,
				"referSentenceyn": "N"
			}
		]
	}
}