{
	"sourceDataInfo": {
		"newsID": "EC_M04_011066",
		"newsCategory": "경제",
		"newsSubcategory": "유통/쇼핑",
		"newsTitle": "불경기에도 중형외제차 수입은 2배 늘어...",
		"newsSubTitle": "",
		"newsContent": "계속된 경기 불황에도 불구하고 지난해 중형 외제차 수입은 오히려 증가한 것으로 나타났다.\n22일 관세청이 발표한 ‘2012년 승용차 수출입 동향’에 따르면 1000cc이하의 경차의 수입은 전년대비 27.3%감소한 반면 1500~2500cc급과 2500cc초과용량의 경유차 수입은 전년 대비 각각 87%, 79%씩 큰폭으로 증가했다.\n수입금액도 1500~2500cc급은 7억8639만 달러에서 14억7041억 달러, 과 2500cc초과급은 4억456만달러에서 7억2423만 달러로 각각 2배가까이 증가했다.\n1500cc이하 경유차의 수입도 전년대비 5.1배 급증했으며, 1000~1500cc휘발류 차량도 22%증가했다.\n반면 3000cc를 초과급 용량의 휘발유차 수입은 전년대비 8.7% 감소했다.\n수입 승용차 가격은 전반적인 하락세를 기록한 가운데 소형 경유차는 31.4%감소했다.\n중형급인 1500~2500cc경유차와 1500~3000cc휘발유차의 대당 평균 수입단가는 전년대비 각각 2.1%, 6.0% 하락했으며, 2500cc초과 차량의 단가는 전년대비 2.0%, 3000cc초과 용량은 전년도 수준을 그대로 유지했다.\n수입대상국은 올해 프랑스산 경ㆍ소형차 비중이 급증한 가운데, 중대형은 독일산이 최다수입국을 기록했다.\n국산차의 수출은 최근 3년 간 꾸준하게 40%대 성장을 유지한 1500cc 이하급 경유차량이 견인하며 올해도 전년대비 41.4% 증가했으며 1000cc이하의 경차도 전년대비 17.7%증가했다.\n반면 대형 승용차는 전년대비 45.7% 대폭 감소했다.\n지난해 승용차의 전체 수출입 동향은 수출은 2.7%(410억 달러, 307만대) 수입은 26.8%(45억 달러, 15만대) 증가했으며, 무역수지는 0.3%(365억 달러) 증가했다.",
		"partNum": "P1",
		"useType": 0,
		"processType": "A",
		"processPattern": "99",
		"processLevel": "하",
		"sentenceCount": 11,
		"sentenceInfo": [
			{
				"sentenceNo": 1,
				"sentenceContent": "계속된 경기 불황에도 불구하고 지난해 중형 외제차 수입은 오히려 증가한 것으로 나타났다.",
				"sentenceSize": 49
			},
			{
				"sentenceNo": 2,
				"sentenceContent": "22일 관세청이 발표한 ‘2012년 승용차 수출입 동향’에 따르면 1000cc이하의 경차의 수입은 전년대비 27.3%감소한 반면 1500~2500cc급과 2500cc초과용량의 경유차 수입은 전년 대비 각각 87%, 79%씩 큰폭으로 증가했다.",
				"sentenceSize": 135
			},
			{
				"sentenceNo": 3,
				"sentenceContent": "수입금액도 1500~2500cc급은 7억8639만 달러에서 14억7041억 달러, 과 2500cc초과급은 4억456만달러에서 7억2423만 달러로 각각 2배가까이 증가했다.",
				"sentenceSize": 96
			},
			{
				"sentenceNo": 4,
				"sentenceContent": "1500cc이하 경유차의 수입도 전년대비 5.1배 급증했으며, 1000~1500cc휘발류 차량도 22%증가했다.",
				"sentenceSize": 62
			},
			{
				"sentenceNo": 5,
				"sentenceContent": "반면 3000cc를 초과급 용량의 휘발유차 수입은 전년대비 8.7% 감소했다.",
				"sentenceSize": 43
			},
			{
				"sentenceNo": 6,
				"sentenceContent": "수입 승용차 가격은 전반적인 하락세를 기록한 가운데 소형 경유차는 31.4%감소했다.",
				"sentenceSize": 47
			},
			{
				"sentenceNo": 7,
				"sentenceContent": "중형급인 1500~2500cc경유차와 1500~3000cc휘발유차의 대당 평균 수입단가는 전년대비 각각 2.1%, 6.0% 하락했으며, 2500cc초과 차량의 단가는 전년대비 2.0%, 3000cc초과 용량은 전년도 수준을 그대로 유지했다.",
				"sentenceSize": 134
			},
			{
				"sentenceNo": 8,
				"sentenceContent": "수입대상국은 올해 프랑스산 경ㆍ소형차 비중이 급증한 가운데, 중대형은 독일산이 최다수입국을 기록했다.",
				"sentenceSize": 56
			},
			{
				"sentenceNo": 9,
				"sentenceContent": "국산차의 수출은 최근 3년 간 꾸준하게 40%대 성장을 유지한 1500cc 이하급 경유차량이 견인하며 올해도 전년대비 41.4% 증가했으며 1000cc이하의 경차도 전년대비 17.7%증가했다.",
				"sentenceSize": 107
			},
			{
				"sentenceNo": 10,
				"sentenceContent": "반면 대형 승용차는 전년대비 45.7% 대폭 감소했다.",
				"sentenceSize": 30
			},
			{
				"sentenceNo": 11,
				"sentenceContent": "지난해 승용차의 전체 수출입 동향은 수출은 2.7%(410억 달러, 307만대) 수입은 26.8%(45억 달러, 15만대) 증가했으며, 무역수지는 0.3%(365억 달러) 증가했다.",
				"sentenceSize": 101
			}
		]
	},
	"labeledDataInfo": {
		"newTitle": "KB국민은행, 'KB연금 컨퍼런스' 온라인 세미나 개최",
		"clickbaitClass": 0,
		"referSentenceInfo": [
			{
				"sentenceNo": 1,
				"referSentenceyn": "N"
			},
			{
				"sentenceNo": 2,
				"referSentenceyn": "N"
			},
			{
				"sentenceNo": 3,
				"referSentenceyn": "N"
			},
			{
				"sentenceNo": 4,
				"referSentenceyn": "N"
			},
			{
				"sentenceNo": 5,
				"referSentenceyn": "N"
			},
			{
				"sentenceNo": 6,
				"referSentenceyn": "N"
			},
			{
				"sentenceNo": 7,
				"referSentenceyn": "N"
			},
			{
				"sentenceNo": 8,
				"referSentenceyn": "N"
			},
			{
				"sentenceNo": 9,
				"referSentenceyn": "N"
			},
			{
				"sentenceNo": 10,
				"referSentenceyn": "N"
			},
			{
				"sentenceNo": 11,
				"referSentenceyn": "N"
			}
		]
	}
}