{
	"sourceDataInfo": {
		"newsID": "EC_M04_009528",
		"newsCategory": "경제",
		"newsSubcategory": "금융/증권",
		"newsTitle": "은행권 대규모 성과급 잔치",
		"newsSubTitle": "국민銀 4년만에 200% 수준 지급… 타 은행도 노사 협상 중",
		"newsContent": "탐욕 논란에 휩싸였던 시중은행권이 대규모 '성과급 잔치'를 벌이고 있다.\n노동조합 측은 사상 최대의 수익을 기록할 것으로 예상되는 만큼, 합리적인 수준을 요구하는 반면, 사측은 잠잠해지고 있는 탐욕 비판이 다시 거세게 몰아칠까 우려하는 분위기다.\n1일 금융권에 따르면, 글로벌 금융위기 이후 사상 최대의 수익을 올린 은행권이 탐욕 논란에도, 성과급을 지급하거나 내부 노·사 간 이견을 조율 중이다.\n국민은행은 월급여의 150%에 달하는 연말성과급을 지급했다.\n2007년 글로벌 금융위기 이후 4년 만이다.\n피복비와 구두비, 연차수당 등까지 포함하면 200% 수준이다.\n은행 관계자는 “4년 동안의 노력을 통해 훌륭한 실적을 기록한 만큼, 성과급도 그에 걸맞게 결정한 것으로 안다”고 말했다.\n신한은행은 월급여의 100~150% 정도의 성과급을 놓고 내부적으로 협의를 진행하고 있다.\n노조는 창립 후 사상 최대 실적이 예상되는 만큼 적어도 합당한 수준의 성과급을 요구한 것으로 전해졌다.\n하나은행 노사도 100%의 성과급 지급안에 대해 협상을 벌이고 있다.\n2년간 성과급을 지급하지 않았던 하나은행은 이미 올 초에 월급여의 100%에 해당하는 성과급을 지급한 바 있다.\n하나은행 노조 관계자는 “사측 역시 노조의 요구를 수긍하는 것으로 전해지고 있지만, 최종 결정은 여전히 미지수”라고 말했다.\n우리은행의 경우 노조가 100%의 성과급 지급을 요구하고 있다.\n6년간 연말 성과급을 받지 못했다는 점에서, 사측을 강하게 압박하고 있다.\n사측 역시 노조의 요구를 충분히 수용하는 분위기지만, 신중한 모양새다.\n최대의 수익 실현과 수수료 장사, 고배당 등 최근 은행권에 대한 여론의 뭇매가 만만치않기 때문이다.\n탐욕 비판과 금융당국의 압박 등으로 각종 수수료 인하하는 등 은행권 입장에선 상당한 양보를 했지만, 자칫 성과급 문제로 또다시 여론이 악화할 수 있어서다.\n시중은행 관계자는 “큰 성과를 올렸다는 점에서 충분한 보상을 받아야 하는데 전적으로 공감한다”며 “하지만, 여러 상황도 고려할 수밖에 없다”고 말했다.\n금융소비자연맹 관계자는 “하반기 들어 은행권이 각종 수수료 인하 등에 나선 건 자발적이 아니라 여론 때문”이라며 “올해에는 은행권 스스로 나섰으면 한다”고 밝혔다.",
		"partNum": "P1",
		"useType": 0,
		"processType": "A",
		"processPattern": "99",
		"processLevel": "하",
		"sentenceCount": 19,
		"sentenceInfo": [
			{
				"sentenceNo": 1,
				"sentenceContent": "탐욕 논란에 휩싸였던 시중은행권이 대규모 '성과급 잔치'를 벌이고 있다.",
				"sentenceSize": 40
			},
			{
				"sentenceNo": 2,
				"sentenceContent": "노동조합 측은 사상 최대의 수익을 기록할 것으로 예상되는 만큼, 합리적인 수준을 요구하는 반면, 사측은 잠잠해지고 있는 탐욕 비판이 다시 거세게 몰아칠까 우려하는 분위기다.",
				"sentenceSize": 96
			},
			{
				"sentenceNo": 3,
				"sentenceContent": "1일 금융권에 따르면, 글로벌 금융위기 이후 사상 최대의 수익을 올린 은행권이 탐욕 논란에도, 성과급을 지급하거나 내부 노·사 간 이견을 조율 중이다.",
				"sentenceSize": 84
			},
			{
				"sentenceNo": 4,
				"sentenceContent": "국민은행은 월급여의 150%에 달하는 연말성과급을 지급했다.",
				"sentenceSize": 33
			},
			{
				"sentenceNo": 5,
				"sentenceContent": "2007년 글로벌 금융위기 이후 4년 만이다.",
				"sentenceSize": 25
			},
			{
				"sentenceNo": 6,
				"sentenceContent": "피복비와 구두비, 연차수당 등까지 포함하면 200% 수준이다.",
				"sentenceSize": 34
			},
			{
				"sentenceNo": 7,
				"sentenceContent": "은행 관계자는 “4년 동안의 노력을 통해 훌륭한 실적을 기록한 만큼, 성과급도 그에 걸맞게 결정한 것으로 안다”고 말했다.",
				"sentenceSize": 68
			},
			{
				"sentenceNo": 8,
				"sentenceContent": "신한은행은 월급여의 100~150% 정도의 성과급을 놓고 내부적으로 협의를 진행하고 있다.",
				"sentenceSize": 50
			},
			{
				"sentenceNo": 9,
				"sentenceContent": "노조는 창립 후 사상 최대 실적이 예상되는 만큼 적어도 합당한 수준의 성과급을 요구한 것으로 전해졌다.",
				"sentenceSize": 57
			},
			{
				"sentenceNo": 10,
				"sentenceContent": "하나은행 노사도 100%의 성과급 지급안에 대해 협상을 벌이고 있다.",
				"sentenceSize": 38
			},
			{
				"sentenceNo": 11,
				"sentenceContent": "2년간 성과급을 지급하지 않았던 하나은행은 이미 올 초에 월급여의 100%에 해당하는 성과급을 지급한 바 있다.",
				"sentenceSize": 62
			},
			{
				"sentenceNo": 12,
				"sentenceContent": "하나은행 노조 관계자는 “사측 역시 노조의 요구를 수긍하는 것으로 전해지고 있지만, 최종 결정은 여전히 미지수”라고 말했다.",
				"sentenceSize": 69
			},
			{
				"sentenceNo": 13,
				"sentenceContent": "우리은행의 경우 노조가 100%의 성과급 지급을 요구하고 있다.",
				"sentenceSize": 35
			},
			{
				"sentenceNo": 14,
				"sentenceContent": "6년간 연말 성과급을 받지 못했다는 점에서, 사측을 강하게 압박하고 있다.",
				"sentenceSize": 41
			},
			{
				"sentenceNo": 15,
				"sentenceContent": "사측 역시 노조의 요구를 충분히 수용하는 분위기지만, 신중한 모양새다.",
				"sentenceSize": 39
			},
			{
				"sentenceNo": 16,
				"sentenceContent": "최대의 수익 실현과 수수료 장사, 고배당 등 최근 은행권에 대한 여론의 뭇매가 만만치않기 때문이다.",
				"sentenceSize": 55
			},
			{
				"sentenceNo": 17,
				"sentenceContent": "탐욕 비판과 금융당국의 압박 등으로 각종 수수료 인하하는 등 은행권 입장에선 상당한 양보를 했지만, 자칫 성과급 문제로 또다시 여론이 악화할 수 있어서다.",
				"sentenceSize": 86
			},
			{
				"sentenceNo": 18,
				"sentenceContent": "시중은행 관계자는 “큰 성과를 올렸다는 점에서 충분한 보상을 받아야 하는데 전적으로 공감한다”며 “하지만, 여러 상황도 고려할 수밖에 없다”고 말했다.",
				"sentenceSize": 84
			},
			{
				"sentenceNo": 19,
				"sentenceContent": "금융소비자연맹 관계자는 “하반기 들어 은행권이 각종 수수료 인하 등에 나선 건 자발적이 아니라 여론 때문”이라며 “올해에는 은행권 스스로 나섰으면 한다”고 밝혔다.",
				"sentenceSize": 91
			}
		]
	},
	"labeledDataInfo": {
		"newTitle": "중기청 지역특화발전특구 5개 신규 지정",
		"clickbaitClass": 0,
		"referSentenceInfo": [
			{
				"sentenceNo": 1,
				"referSentenceyn": "N"
			},
			{
				"sentenceNo": 2,
				"referSentenceyn": "N"
			},
			{
				"sentenceNo": 3,
				"referSentenceyn": "N"
			},
			{
				"sentenceNo": 4,
				"referSentenceyn": "N"
			},
			{
				"sentenceNo": 5,
				"referSentenceyn": "N"
			},
			{
				"sentenceNo": 6,
				"referSentenceyn": "N"
			},
			{
				"sentenceNo": 7,
				"referSentenceyn": "N"
			},
			{
				"sentenceNo": 8,
				"referSentenceyn": "N"
			},
			{
				"sentenceNo": 9,
				"referSentenceyn": "N"
			},
			{
				"sentenceNo": 10,
				"referSentenceyn": "N"
			},
			{
				"sentenceNo": 11,
				"referSentenceyn": "N"
			},
			{
				"sentenceNo": 12,
				"referSentenceyn": "N"
			},
			{
				"sentenceNo": 13,
				"referSentenceyn": "N"
			},
			{
				"sentenceNo": 14,
				"referSentenceyn": "N"
			},
			{
				"sentenceNo": 15,
				"referSentenceyn": "N"
			},
			{
				"sentenceNo": 16,
				"referSentenceyn": "N"
			},
			{
				"sentenceNo": 17,
				"referSentenceyn": "N"
			},
			{
				"sentenceNo": 18,
				"referSentenceyn": "N"
			},
			{
				"sentenceNo": 19,
				"referSentenceyn": "N"
			}
		]
	}
}