{
	"sourceDataInfo": {
		"newsID": "ET_M13_022467",
		"newsCategory": "연예",
		"newsSubcategory": "방송",
		"newsTitle": "‘아수라장’ 김미려, 남편과 셋째 ‘동상이몽’",
		"newsSubTitle": "",
		"newsContent": "개그우먼 김미려가 남편과의 금실 스토리로 박지윤×민혜연×정시아를 초토화 시킨다. 10일 방송되는 SBS FiL ‘아수라장’에는 김미려가 게스트로 등장해 오늘의 주제인 최고 인싸 엄마 되기 주제로 토크를 나눈다.\n김미려는 자녀 이야기를 하면서 남편인 배우 정성윤과의 셋째 계획에 대한 에피소드를 털어놓는다.\nMC박지윤이 김미려에게 “셋째 계획이 있는지?” 물어보자, 김미려는 “계획 중”이라고 밝혔다.\n박지윤은 남편이랑 합의된 게 맞냐고 의심하자, 김미려는 “남편이 왔다 갔다 한다”고 고백한다.\n이어, 남편이 가끔 “하루 정도 아무것도 안 하고 싶다” “파스타가 먹고 싶다” 등의 푸념을 한다며 육아 스트레스를 가늠하게 해 웃픈 공감을 자아낸다.\n또, 예쁜 연예인 2세로 김미려의 딸 ‘모아’ 가 널리 알려져 있다고 하자, MC박지윤은 “남편을 만나길 잘했다고 생각한 적이 있는지? 아이를 예쁘게 낳기 위해 배우자를 선택하는 건 아니지만” 이라며 질문하자, 김미려는 “저는 그랬어요” 라고 해 당황하게 했다.\n덧붙여 “어제 남편이랑 딸이랑 서있는 모습을 보는데 딸이 키가 많이 컸다” 며 키가 183cm 인 장신 남편을 선택한 이유를 자랑해 부러움을 산다. ‘최고의 인싸 엄마’가 되기 위해 엄마들은 어떤 것들을 알고 있어야 하는지, 요즘 엄마들이 자녀를 위해 해야 하는 것은 무엇이 있는지, 육아맘을 위한 실용 꿀팁을 전달하는 것은 물론 그녀들의 3인 3색 자녀 훈육법까지 8월 10일 화요일 밤 11시 ‘은밀하고 비밀스런 토크쇼 아수라장’에서 공개된다.",
		"partNum": "P1",
		"useType": 0,
		"processType": "A",
		"processPattern": "99",
		"processLevel": "하",
		"sentenceCount": 7,
		"sentenceInfo": [
			{
				"sentenceNo": 1,
				"sentenceContent": "개그우먼 김미려가 남편과의 금실 스토리로 박지윤×민혜연×정시아를 초토화 시킨다. 10일 방송되는 SBS FiL ‘아수라장’에는 김미려가 게스트로 등장해 오늘의 주제인 최고 인싸 엄마 되기 주제로 토크를 나눈다.",
				"sentenceSize": 117
			},
			{
				"sentenceNo": 2,
				"sentenceContent": "김미려는 자녀 이야기를 하면서 남편인 배우 정성윤과의 셋째 계획에 대한 에피소드를 털어놓는다.",
				"sentenceSize": 52
			},
			{
				"sentenceNo": 3,
				"sentenceContent": "MC박지윤이 김미려에게 “셋째 계획이 있는지?” 물어보자, 김미려는 “계획 중”이라고 밝혔다.",
				"sentenceSize": 52
			},
			{
				"sentenceNo": 4,
				"sentenceContent": "박지윤은 남편이랑 합의된 게 맞냐고 의심하자, 김미려는 “남편이 왔다 갔다 한다”고 고백한다.",
				"sentenceSize": 52
			},
			{
				"sentenceNo": 5,
				"sentenceContent": "이어, 남편이 가끔 “하루 정도 아무것도 안 하고 싶다” “파스타가 먹고 싶다” 등의 푸념을 한다며 육아 스트레스를 가늠하게 해 웃픈 공감을 자아낸다.",
				"sentenceSize": 84
			},
			{
				"sentenceNo": 6,
				"sentenceContent": "또, 예쁜 연예인 2세로 김미려의 딸 ‘모아’ 가 널리 알려져 있다고 하자, MC박지윤은 “남편을 만나길 잘했다고 생각한 적이 있는지? 아이를 예쁘게 낳기 위해 배우자를 선택하는 건 아니지만” 이라며 질문하자, 김미려는 “저는 그랬어요” 라고 해 당황하게 했다.",
				"sentenceSize": 146
			},
			{
				"sentenceNo": 7,
				"sentenceContent": "덧붙여 “어제 남편이랑 딸이랑 서있는 모습을 보는데 딸이 키가 많이 컸다” 며 키가 183cm 인 장신 남편을 선택한 이유를 자랑해 부러움을 산다. ‘최고의 인싸 엄마’가 되기 위해 엄마들은 어떤 것들을 알고 있어야 하는지, 요즘 엄마들이 자녀를 위해 해야 하는 것은 무엇이 있는지, 육아맘을 위한 실용 꿀팁을 전달하는 것은 물론 그녀들의 3인 3색 자녀 훈육법까지 8월 10일 화요일 밤 11시 ‘은밀하고 비밀스런 토크쇼 아수라장’에서 공개된다.",
				"sentenceSize": 250
			}
		]
	},
	"labeledDataInfo": {
		"newTitle": "전지현 측 \\\"일부에만 임대료 감면? 중간 관리인 착오…누락된 곳 조치\\\"",
		"clickbaitClass": 0,
		"referSentenceInfo": [
			{
				"sentenceNo": 1,
				"referSentenceyn": "N"
			},
			{
				"sentenceNo": 2,
				"referSentenceyn": "N"
			},
			{
				"sentenceNo": 3,
				"referSentenceyn": "N"
			},
			{
				"sentenceNo": 4,
				"referSentenceyn": "N"
			},
			{
				"sentenceNo": 5,
				"referSentenceyn": "N"
			},
			{
				"sentenceNo": 6,
				"referSentenceyn": "N"
			},
			{
				"sentenceNo": 7,
				"referSentenceyn": "N"
			}
		]
	}
}