{
	"sourceDataInfo": {
		"newsID": "ET_M13_026933",
		"newsCategory": "연예",
		"newsSubcategory": "연예일반",
		"newsTitle": "권혁현, ‘키마이라’ 출연 확정…박해수 절친 이건영 役[공식]",
		"newsSubTitle": "",
		"newsContent": "배우 권혁현이 드라마 ‘키마이라’에 출연을 확정지었다.\n소속사 에이엘 엔터테인먼트 (AL ENT)는 “권혁현이 OCN 새 토일 드라마 ‘키마이라’에 출연한다”고 전했다. ‘키마이라’는 강력계 형사 재환 (박해수 분), 프로파일러 유진 (수현 분), 외과의사 중엽 (이희준 분)이 각자 다른 목적으로 35년 만에 다시 시작된 연쇄 폭발 사건, 일명 ‘키마이라’의 진실을 쫓는 내용을 담은 추적 스릴러물로 ‘구여친클럽’ ‘아이 엠 샘’의 이진매 작가와 ‘해를 품은 달’, ‘로열패밀리’의 김도훈PD가 의기투합해 뜨거운 관심을 모으고 있다.\n권혁현은 극 중 강력반 특별 수사팀 요원 이건영을 연기한다.\n이건영은 재환과 단짝인 후배 형사다.\n차재환 형사를 평소 존경하고 배우고 싶은 마음에 따라하는 귀여운 인물이다.\n쉬는 날에는 수사물 미드를 즐겨보며, FBI 출신인 유진을 선망하는 밝은 성격의 청년이다.\n권혁현은 지난해 채널A 드라마 ‘거짓말의 거짓말’에서 상상 초월 반전을 선사하며 강렬한 인상을 남겼다.\n이번 OCN ‘키마이라’에서는 어떤 모습을 보여줄지 기대가 모인다.\n한편, 권혁현이 출연하는 OCN 새 드라마 ‘키마이라’는 오는 30일 오후 10시30분에 첫 방송된다.",
		"partNum": "P1",
		"useType": 0,
		"processType": "A",
		"processPattern": "99",
		"processLevel": "하",
		"sentenceCount": 9,
		"sentenceInfo": [
			{
				"sentenceNo": 1,
				"sentenceContent": "배우 권혁현이 드라마 ‘키마이라’에 출연을 확정지었다.",
				"sentenceSize": 30
			},
			{
				"sentenceNo": 2,
				"sentenceContent": "소속사 에이엘 엔터테인먼트 (AL ENT)는 “권혁현이 OCN 새 토일 드라마 ‘키마이라’에 출연한다”고 전했다. ‘키마이라’는 강력계 형사 재환 (박해수 분), 프로파일러 유진 (수현 분), 외과의사 중엽 (이희준 분)이 각자 다른 목적으로 35년 만에 다시 시작된 연쇄 폭발 사건, 일명 ‘키마이라’의 진실을 쫓는 내용을 담은 추적 스릴러물로 ‘구여친클럽’ ‘아이 엠 샘’의 이진매 작가와 ‘해를 품은 달’, ‘로열패밀리’의 김도훈PD가 의기투합해 뜨거운 관심을 모으고 있다.",
				"sentenceSize": 268
			},
			{
				"sentenceNo": 3,
				"sentenceContent": "권혁현은 극 중 강력반 특별 수사팀 요원 이건영을 연기한다.",
				"sentenceSize": 33
			},
			{
				"sentenceNo": 4,
				"sentenceContent": "이건영은 재환과 단짝인 후배 형사다.",
				"sentenceSize": 20
			},
			{
				"sentenceNo": 5,
				"sentenceContent": "차재환 형사를 평소 존경하고 배우고 싶은 마음에 따라하는 귀여운 인물이다.",
				"sentenceSize": 41
			},
			{
				"sentenceNo": 6,
				"sentenceContent": "쉬는 날에는 수사물 미드를 즐겨보며, FBI 출신인 유진을 선망하는 밝은 성격의 청년이다.",
				"sentenceSize": 50
			},
			{
				"sentenceNo": 7,
				"sentenceContent": "권혁현은 지난해 채널A 드라마 ‘거짓말의 거짓말’에서 상상 초월 반전을 선사하며 강렬한 인상을 남겼다.",
				"sentenceSize": 57
			},
			{
				"sentenceNo": 8,
				"sentenceContent": "이번 OCN ‘키마이라’에서는 어떤 모습을 보여줄지 기대가 모인다.",
				"sentenceSize": 37
			},
			{
				"sentenceNo": 9,
				"sentenceContent": "한편, 권혁현이 출연하는 OCN 새 드라마 ‘키마이라’는 오는 30일 오후 10시30분에 첫 방송된다.",
				"sentenceSize": 57
			}
		]
	},
	"labeledDataInfo": {
		"newTitle": "‘너가속’ 김무준×서지혜의 청춘 케미도 有",
		"clickbaitClass": 0,
		"referSentenceInfo": [
			{
				"sentenceNo": 1,
				"referSentenceyn": "N"
			},
			{
				"sentenceNo": 2,
				"referSentenceyn": "N"
			},
			{
				"sentenceNo": 3,
				"referSentenceyn": "N"
			},
			{
				"sentenceNo": 4,
				"referSentenceyn": "N"
			},
			{
				"sentenceNo": 5,
				"referSentenceyn": "N"
			},
			{
				"sentenceNo": 6,
				"referSentenceyn": "N"
			},
			{
				"sentenceNo": 7,
				"referSentenceyn": "N"
			},
			{
				"sentenceNo": 8,
				"referSentenceyn": "N"
			},
			{
				"sentenceNo": 9,
				"referSentenceyn": "N"
			}
		]
	}
}